[
  {
    "id": 1,
    "title": "New Job Match",
    "message": "Senior Frontend Developer position at TechCorp Solutions matches your profile",
    "type": "job_match",
    "date": "2024-01-16",
    "read": false
  },
  {
    "id": 2,
    "title": "Interview Invitation",
    "message": "You have been invited for an interview at DataMinds Analytics",
    "type": "interview",
    "date": "2024-01-15",
    "read": false
  },
  {
    "id": 3,
    "title": "Application Viewed",
    "message": "Your application for Product Manager at InnovateLabs has been viewed",
    "type": "application_update",
    "date": "2024-01-14",
    "read": true
  },
  {
    "id": 4,
    "title": "Profile Update",
    "message": "Complete your profile to increase visibility to recruiters",
    "type": "profile",
    "date": "2024-01-13",
    "read": true
  },
  {
    "id": 5,
    "title": "Offer Update",
    "message": "Congratulations! You have received an offer from CloudTech Infrastructure",
    "type": "offer",
    "date": "2024-01-12",
    "read": false
  }
]